cproton_ffi.abi3.so
cproton.py
python_qpid_proton_wheel-0.39.0.dist-info/RECORD
python_qpid_proton_wheel-0.39.0.dist-info/WHEEL
python_qpid_proton_wheel-0.39.0.dist-info/top_level.txt
python_qpid_proton_wheel-0.39.0.dist-info/METADATA
proton/_tracing.py
proton/_wrapper.py
proton/_data.py
proton/tracing.py
proton/reactor.py
proton/_reactor.py
proton/_delivery.py
proton/_handler.py
proton/_io.py
proton/_url.py
proton/_handlers.py
proton/_common.py
proton/handlers.py
proton/__init__.py
proton/_transport.py
proton/_message.py
proton/utils.py
proton/_events.py
proton/_endpoints.py
proton/_selectable.py
proton/_condition.py
proton/_exceptions.py
proton/_utils.py
