Metadata-Version: 2.1
Name: python-qpid-proton-wheel
Version: 0.39.0
Summary: An AMQP based messaging library.
Home-page: http://qpid.apache.org/proton/
Author: Apache Qpid
Author-email: users@qpid.apache.org
License: Apache Software License
Classifier: License :: OSI Approved :: Apache Software License
Classifier: Intended Audience :: Developers
Classifier: Programming Language :: Python
Classifier: Programming Language :: Python :: 3
Classifier: Programming Language :: Python :: 3 :: Only
Classifier: Programming Language :: Python :: 3.8
Classifier: Programming Language :: Python :: 3.9
Classifier: Programming Language :: Python :: 3.10
Classifier: Programming Language :: Python :: 3.11
Requires-Dist: cffi >=1.0.0
Provides-Extra: opentracing
Requires-Dist: opentracing ; extra == 'opentracing'
Requires-Dist: jaeger-client ; extra == 'opentracing'
